xSL06
