Metadata-Version: 2.1
Name: xinabox-SL06
Version: 0.0.5
Summary: Proximity, gesture, light and colour sensor
Home-page: https://github.com/xinabox/Python-SL06
Author: Luqmaan Baboo
Author-email: luqmaanbaboo@gmail.com
License: UNKNOWN
Platform: UNKNOWN
Classifier: Programming Language :: Python :: 3
Classifier: License :: OSI Approved :: MIT License
Classifier: Operating System :: OS Independent
Requires-Python: >=3.6
